circulation/__init__.py
circulation/base.py
circulation/bestel.py
circulation/log.py
circulation/regazzoni2020.py
circulation/time_varying_elastance.py
circulation/units.py
circulation/zenker.py
circulation-0.2.0.dist-info/licenses/LICENSE
circulation-0.2.0.dist-info/METADATA
circulation-0.2.0.dist-info/WHEEL
circulation-0.2.0.dist-info/top_level.txt
circulation-0.2.0.dist-info/RECORD
