Metadata-Version: 2.4
Name: circulation
Version: 0.2.0
Summary: Closed loop blood circulation model in FEniCS
Author-email: Henrik Finsberg <henriknf@simula.no>
License-Expression: MIT
Requires-Python: >=3.11
License-File: LICENSE
Requires-Dist: numpy
Requires-Dist: pint
Requires-Dist: rich
Provides-Extra: test
Requires-Dist: pytest; extra == "test"
Requires-Dist: pytest-cov; extra == "test"
Requires-Dist: scipy; extra == "test"
Provides-Extra: demos
Requires-Dist: matplotlib; extra == "demos"
Requires-Dist: scipy; extra == "demos"
Provides-Extra: docs
Requires-Dist: jupyter-book<2.0; extra == "docs"
Requires-Dist: jupytext; extra == "docs"
Requires-Dist: circulation[demos]; extra == "docs"
Requires-Dist: sphinxcontrib-bibtex; extra == "docs"
Provides-Extra: all
Requires-Dist: circulation[test]; extra == "all"
Requires-Dist: circulation[plot]; extra == "all"
Requires-Dist: circulation[docs]; extra == "all"
Requires-Dist: circulation[dev]; extra == "all"
Dynamic: license-file
